pyctakes/__init__.py
pyctakes/cli.py
pyctakes/pipeline.py
pyctakes/types.py
pyctakes/agents/__init__.py
pyctakes/agents/prompts.py
pyctakes/annotators/__init__.py
pyctakes/annotators/assertion.py
pyctakes/annotators/base.py
pyctakes/annotators/ner.py
pyctakes/annotators/sections.py
pyctakes/annotators/tokenization.py
pyctakes/annotators/umls.py
pyctakes-1.0.0.dist-info/licenses/LICENSE
pyctakes-1.0.0.dist-info/METADATA
pyctakes-1.0.0.dist-info/WHEEL
pyctakes-1.0.0.dist-info/entry_points.txt
pyctakes-1.0.0.dist-info/top_level.txt
pyctakes-1.0.0.dist-info/RECORD
