Metadata-Version: 2.4
Name: pyctakes
Version: 1.0.0
Summary: Python-native clinical NLP framework mirroring Apache cTAKES functionality
Author-email: Sonish Sivarajkumar <sonish.sivarajkumar@gmail.com>
Maintainer-email: Sonish Sivarajkumar <sonish.sivarajkumar@gmail.com>
License-Expression: Apache-2.0
Project-URL: Homepage, https://github.com/sonishsivarajkumar/PyCTAKES
Project-URL: Documentation, https://sonishsivarajkumar.github.io/PyCTAKES/
Project-URL: Repository, https://github.com/sonishsivarajkumar/PyCTAKES.git
Project-URL: Bug Tracker, https://github.com/sonishsivarajkumar/PyCTAKES/issues
Keywords: nlp,clinical,medical,ctakes,umls,healthcare
Classifier: Development Status :: 5 - Production/Stable
Classifier: Intended Audience :: Healthcare Industry
Classifier: Intended Audience :: Science/Research
Classifier: Operating System :: OS Independent
Classifier: Programming Language :: Python :: 3
Classifier: Programming Language :: Python :: 3.8
Classifier: Programming Language :: Python :: 3.9
Classifier: Programming Language :: Python :: 3.10
Classifier: Programming Language :: Python :: 3.11
Classifier: Topic :: Scientific/Engineering :: Artificial Intelligence
Classifier: Topic :: Scientific/Engineering :: Medical Science Apps.
Classifier: Topic :: Text Processing :: Linguistic
Requires-Python: >=3.8
License-File: LICENSE
Requires-Dist: spacy>=3.4.0
Requires-Dist: stanza>=1.4.0
Requires-Dist: transformers>=4.20.0
Requires-Dist: torch>=1.12.0
Requires-Dist: numpy>=1.21.0
Requires-Dist: pandas>=1.3.0
Requires-Dist: pydantic>=1.9.0
Requires-Dist: click>=8.0.0
Requires-Dist: fastapi>=0.75.0
Requires-Dist: uvicorn>=0.17.0
Requires-Dist: langchain>=0.0.100
Requires-Dist: flashtext>=2.7
Requires-Dist: pyyaml>=6.0
Requires-Dist: tqdm>=4.64.0
Requires-Dist: requests>=2.28.0
Requires-Dist: aiofiles>=0.8.0
Provides-Extra: dev
Requires-Dist: pytest>=7.0.0; extra == "dev"
Requires-Dist: pytest-cov>=3.0.0; extra == "dev"
Requires-Dist: pytest-asyncio>=0.18.0; extra == "dev"
Requires-Dist: black>=22.0.0; extra == "dev"
Requires-Dist: isort>=5.10.0; extra == "dev"
Requires-Dist: flake8>=4.0.0; extra == "dev"
Requires-Dist: mypy>=0.950; extra == "dev"
Requires-Dist: pre-commit>=2.17.0; extra == "dev"
Provides-Extra: docs
Requires-Dist: sphinx>=4.5.0; extra == "docs"
Requires-Dist: sphinx-rtd-theme>=1.0.0; extra == "docs"
Requires-Dist: sphinx-autodoc-typehints>=1.17.0; extra == "docs"
Requires-Dist: myst-parser>=0.17.0; extra == "docs"
Provides-Extra: dask
Requires-Dist: dask[complete]>=2022.0.0; extra == "dask"
Provides-Extra: all
Requires-Dist: pyctakes[dask,dev,docs]; extra == "all"
Dynamic: license-file
